py.typed
pyspart\__init__.py
pyspart\__init__.pyi
pyspart\py.typed
pyspart\pyspart.pyd
pyspart-0.5.0.dist-info\METADATA
pyspart-0.5.0.dist-info\WHEEL
pyspart-0.5.0.dist-info\licenses\LICENSE
pyspart.pyi
pyspart-0.5.0.dist-info\RECORD
