Metadata-Version: 2.4
Name: pyspart
Version: 0.5.0
Classifier: Development Status :: 4 - Beta
Classifier: Intended Audience :: Developers
Classifier: License :: OSI Approved :: MIT License
Classifier: Programming Language :: Rust
Classifier: Programming Language :: Python :: 3
Classifier: Programming Language :: Python :: 3.10
Classifier: Programming Language :: Python :: 3.11
Classifier: Programming Language :: Python :: 3.12
Classifier: Programming Language :: Python :: 3.13
Classifier: Programming Language :: Python :: 3.14
Classifier: Programming Language :: Python :: Implementation :: PyPy
Classifier: Topic :: Software Development :: Libraries
Classifier: Topic :: Software Development :: Libraries :: Python Modules
License-File: LICENSE
Summary: Python bindings for Spart library
Keywords: quadtree,kdtree,r-tree,octree,spatial-index
Author-email: Hassan Abedi <hassan.abedi.t+pyspart@gmail.com>
Maintainer-email: Hassan Abedi <hassan.abedi.t+pyspart@gmail.com>
License: MIT
Requires-Python: >=3.10
Project-URL: documentation, https://github.com/habedi/spart/tree/main/pyspart
Project-URL: homepage, https://github.com/habedi/spart
Project-URL: repository, https://github.com/habedi/spart/tree/main/pyspart
